sithon/__init__.py
sithon/__main__.py
sithon/log.py
sithon/sithon.py
sithon/testing.py
Sithon-0.0.4.dist-info/LICENSE
Sithon-0.0.4.dist-info/METADATA
Sithon-0.0.4.dist-info/WHEEL
Sithon-0.0.4.dist-info/top_level.txt
Sithon-0.0.4.dist-info/RECORD
